{
  "filing_type": "GSTR-3B",
  "period": "2024-04",
  "gstin": "27AAAAA0000A1Z5",
  "schema_version": "1.0.0",
  "generated_at": "2024-04-30T12:00:00.000Z",
  "outwardTaxable": {
    "taxable_value": "150000",
    "cgst": "13500",
    "sgst": "13500",
    "igst": "0"
  },
  "zeroRated": {
    "taxable_value": "20000"
  },
  "exempt": {
    "taxable_value": "10000"
  },
  "reverseCharge": {
    "tax": "0"
  },
  "itc": {
    "cgst": "2000",
    "sgst": "2000",
    "igst": "0"
  },
  "taxLiability": {
    "total": "23000"
  }
}
